fmconcert/__init__.py
fmconcert/cli.py
fmconcert/fmconcert.py
fmconcert-0.3.0.dist-info/AUTHORS.rst
fmconcert-0.3.0.dist-info/LICENSE
fmconcert-0.3.0.dist-info/METADATA
fmconcert-0.3.0.dist-info/WHEEL
fmconcert-0.3.0.dist-info/entry_points.txt
fmconcert-0.3.0.dist-info/top_level.txt
fmconcert-0.3.0.dist-info/RECORD
