Metadata-Version: 2.1
Name: fmconcert
Version: 0.3.0
Summary: Download France Musique concert file by scrapping on broadcast webpage
Home-page: https://gitlab.com/boileaum/fmconcert
Author: Matthieu Boileau
Author-email: matthieu.boileau@gmail.com
License: MIT license
Keywords: fmconcert
Platform: UNKNOWN
Classifier: Development Status :: 2 - Pre-Alpha
Classifier: Intended Audience :: Developers
Classifier: License :: OSI Approved :: MIT License
Classifier: Natural Language :: English
Classifier: Programming Language :: Python :: 2
Classifier: Programming Language :: Python :: 2.6
Classifier: Programming Language :: Python :: 2.7
Classifier: Programming Language :: Python :: 3
Classifier: Programming Language :: Python :: 3.3
Classifier: Programming Language :: Python :: 3.4
Classifier: Programming Language :: Python :: 3.5
Requires-Dist: bs4
Requires-Dist: progressbar
